topkappy/FormattedKappaError.py
topkappy/KappaClasses.py
topkappy/KappaModel.py
topkappy/__init__.py
topkappy/agents_graphs.py
topkappy/plot_simulation_time_series.py
topkappy/version.py
topkappy-0.2.4.dist-info/LICENCE.txt
topkappy-0.2.4.dist-info/METADATA
topkappy-0.2.4.dist-info/WHEEL
topkappy-0.2.4.dist-info/top_level.txt
topkappy-0.2.4.dist-info/RECORD
