Metadata-Version: 2.1
Name: topkappy
Version: 0.2.4
Summary: Pythonic wrapper for the Kappa language (bio simulations)
Home-page: https://github.com/Edinburgh-Genome-Foundry/topkappy
Author: Zulko
Author-email: UNKNOWN
License: MIT
Keywords: simulation biology modeling complex kappa binding
Platform: UNKNOWN
Requires-Dist: kappy (<4.1)
Requires-Dist: networkx
Requires-Dist: matplotlib
Requires-Dist: numpy
Requires-Dist: termcolor
